trycortex/__init__.py
trycortex/api.py
trycortex/callables/__init__.py
trycortex/callables/base.py
trycortex/callables/blocks.py
trycortex/cli/__init__.py
trycortex/cli/auth/__init__.py
trycortex/cli/auth/commands.py
trycortex/cli/callable/__init__.py
trycortex/cli/callable/callable_config.py
trycortex/cli/callable/commands.py
trycortex/cli/cli.py
trycortex/cli/utils.py
trycortex-1.2.2.dist-info/METADATA
trycortex-1.2.2.dist-info/WHEEL
trycortex-1.2.2.dist-info/entry_points.txt
trycortex-1.2.2.dist-info/RECORD
