Metadata-Version: 2.1
Name: trycortex
Version: 1.2.2
Summary: Python library for Cortex
Author: Charles
Author-email: charlespun6@gmail.com
Requires-Python: >=3.7,<4.0
Classifier: Programming Language :: Python :: 3
Classifier: Programming Language :: Python :: 3.7
Classifier: Programming Language :: Python :: 3.8
Classifier: Programming Language :: Python :: 3.9
Classifier: Programming Language :: Python :: 3.10
Classifier: Programming Language :: Python :: 3.11
Requires-Dist: click (>=8.1.5,<9.0.0)
Requires-Dist: dataclasses-json (>=0.5.9,<0.6.0)
Requires-Dist: pathlib (>=1.0.1,<2.0.0)
Requires-Dist: pytest (>=7.4.0,<8.0.0)
Requires-Dist: pyyaml (>=6.0,<7.0)
Requires-Dist: requests (>=2.31.0,<3.0.0)
Requires-Dist: validators (>=0.20.0,<0.21.0)
